MANIFEST.in
README.rst
requirements-docs.txt
requirements-test.txt
requirements.txt
setup.cfg
setup.py
src/django_simple_permissions.egg-info/PKG-INFO
src/django_simple_permissions.egg-info/SOURCES.txt
src/django_simple_permissions.egg-info/dependency_links.txt
src/django_simple_permissions.egg-info/requires.txt
src/django_simple_permissions.egg-info/top_level.txt
src/django_simple_permissions.egg-info/zip-safe
src/simple_permissions/__init__.py
src/simple_permissions/compat.py
src/simple_permissions/conf.py
src/simple_permissions/handlers.py
src/simple_permissions/models.py
src/simple_permissions/decorators/__init__.py
src/simple_permissions/decorators/classbase.py
src/simple_permissions/decorators/functionbase.py
src/simple_permissions/decorators/methodbase.py
src/simple_permissions/decorators/permission_required.py
src/simple_permissions/decorators/utils.py
src/simple_permissions/logics/__init__.py
src/simple_permissions/logics/base.py
src/simple_permissions/templatetags/__init__.py
src/simple_permissions/templatetags/permissionif.py
src/simple_permissions/utils/__init__.py
src/simple_permissions/utils/autodiscover.py
src/simple_permissions/utils/field_lookup.py
src/simple_permissions/utils/filters.py
src/simple_permissions/utils/handlers.py
src/simple_permissions/utils/logics.py
src/simple_permissions/utils/permissions.py