Metadata-Version: 1.1
Name: django-simple-permissions
Version: 0.6.2
Summary: A enhanced permission system which enable logical permissionsystems to complex permissions
Home-page: https://github.com/giovabal/django-simple-permissions
Author: Giovabal
Author-email: giovabal@gmail.com
License: MIT
Download-URL: https://github.com/giovabal/django-simple-permissions/tarball/master
Keywords: django object logical permission auth authentication
Platform: UNKNOWN
Classifier: Development Status :: 3 - Alpha
Classifier: Environment :: Web Environment
Classifier: Framework :: Django
Classifier: Intended Audience :: Developers
Classifier: License :: OSI Approved :: MIT License
Classifier: Programming Language :: Python
Classifier: Programming Language :: Python :: 2
Classifier: Programming Language :: Python :: 2.6
Classifier: Programming Language :: Python :: 2.7
Classifier: Programming Language :: Python :: 3
Classifier: Programming Language :: Python :: 3.3
Classifier: Programming Language :: Python :: 3.4
Classifier: Programming Language :: Python :: 3.5
Classifier: Topic :: Internet :: WWW/HTTP
Classifier: Topic :: Software Development :: Libraries
Classifier: Topic :: Software Development :: Libraries :: Application Frameworks
Classifier: Topic :: Software Development :: Libraries :: Python Modules
